{
    "AX": {
        "error": 0.006532889376038149, 
        "filter_outliers_dict": {
            "filter_outliers": true, 
            "iterations": 1, 
            "std_devs": 2
        }, 
        "fit": "average", 
        "value": -0.09225372690837216
    }, 
    "CDD": {
        "error": 3.297080768692644e-05, 
        "filter_outliers_dict": {
            "filter_outliers": true, 
            "iterations": 1, 
            "std_devs": 10
        }, 
        "fit": "average", 
        "value": 0.0003944933500007609
    }, 
    "H1": {
        "error": 0.005106560163918972, 
        "filter_outliers_dict": {
            "filter_outliers": true, 
            "iterations": 1, 
            "std_devs": 2
        }, 
        "fit": "average", 
        "value": -5.1320341095141515e-05
    }, 
    "H2": {
        "error": 0.008470723057209507, 
        "filter_outliers_dict": {
            "filter_outliers": true, 
            "iterations": 1, 
            "std_devs": 2
        }, 
        "fit": "average", 
        "value": -0.2175330282353846
    }, 
    "L1": {
        "error": 0.0036390626686945036, 
        "filter_outliers_dict": {
            "filter_outliers": true, 
            "iterations": 1, 
            "std_devs": 2
        }, 
        "fit": "average", 
        "value": -0.020210735844319958
    }, 
    "L2": {
        "error": 0.00637077093833599, 
        "filter_outliers_dict": {
            "filter_outliers": true, 
            "iterations": 1, 
            "std_devs": 2
        }, 
        "fit": "average", 
        "value": -0.02496030014055409
    }
}