{
    "AX": {
        "error": 0.005284692412904632, 
        "filter_outliers_dict": {
            "filter_outliers": true, 
            "iterations": 1, 
            "std_devs": 2
        }, 
        "fit": "average", 
        "value": -0.06926385980179486
    }, 
    "CDD": {
        "error": 5.476327972284686e-06, 
        "filter_outliers_dict": {
            "filter_outliers": true, 
            "iterations": 1, 
            "std_devs": 10
        }, 
        "fit": "average", 
        "value": 2.605144698394799e-05
    }, 
    "H1": {
        "error": 0.003880631789111066, 
        "filter_outliers_dict": {
            "filter_outliers": true, 
            "iterations": 1, 
            "std_devs": 2
        }, 
        "fit": "average", 
        "value": -0.02872953927115759
    }, 
    "H2": {
        "error": 0.005351206737183363, 
        "filter_outliers_dict": {
            "filter_outliers": true, 
            "iterations": 1, 
            "std_devs": 2
        }, 
        "fit": "average", 
        "value": -0.18338645929668768
    }, 
    "L1": {
        "error": 0.0017622778406878401, 
        "filter_outliers_dict": {
            "filter_outliers": true, 
            "iterations": 1, 
            "std_devs": 2
        }, 
        "fit": "average", 
        "value": -0.022076394895793005
    }, 
    "L2": {
        "error": 0.004510181140254187, 
        "filter_outliers_dict": {
            "filter_outliers": true, 
            "iterations": 1, 
            "std_devs": 2
        }, 
        "fit": "average", 
        "value": -0.02490195552422275
    }
}