{
    "Ar36": {
        "error": 0.0002426374093377454, 
        "filter_outliers_dict": {
            "filter_outliers": true, 
            "iterations": 1, 
            "std_devs": 2
        }, 
        "fit": "Linear", 
        "value": 0.009351030066193217
    }, 
    "Ar37": {
        "error": 0.01019089616980118, 
        "filter_outliers_dict": {
            "filter_outliers": true, 
            "iterations": 1, 
            "std_devs": 2
        }, 
        "fit": "linear", 
        "value": 0.2942001807022083
    }, 
    "Ar38": {
        "error": 0.003830482192461252, 
        "filter_outliers_dict": {
            "filter_outliers": true, 
            "iterations": 1, 
            "std_devs": 2
        }, 
        "fit": "linear", 
        "value": 0.9408802122200021
    }, 
    "Ar39": {
        "error": 0.01933022002695693, 
        "filter_outliers_dict": {
            "filter_outliers": true, 
            "iterations": 1, 
            "std_devs": 2
        }, 
        "fit": "Linear", 
        "value": 73.34796308477952
    }, 
    "Ar40": {
        "error": 0.03200794412831171, 
        "filter_outliers_dict": {
            "filter_outliers": true, 
            "iterations": 1, 
            "std_devs": 2
        }, 
        "fit": "Linear", 
        "value": 293.2691414552501
    }, 
    "PM41": {
        "error": 0.05360834565471785, 
        "filter_outliers_dict": {
            "filter_outliers": false, 
            "iterations": 1, 
            "std_devs": 2
        }, 
        "fit": "linear", 
        "value": -0.17435372679163103
    }
}