{
    "Ar36": {
        "error": 0.0009022288434249868, 
        "filter_outliers_dict": {
            "filter_outliers": true, 
            "iterations": 1, 
            "std_devs": 2
        }, 
        "fit": "Parabolic", 
        "value": 0.2802717576239159
    }, 
    "Ar37": {
        "error": 0.00552622337986264, 
        "filter_outliers_dict": {
            "filter_outliers": true, 
            "iterations": 1, 
            "std_devs": 2
        }, 
        "fit": "linear", 
        "value": 0.022433301356858715
    }, 
    "Ar38": {
        "error": 0.002234248440443227, 
        "filter_outliers_dict": {
            "filter_outliers": true, 
            "iterations": 1, 
            "std_devs": 2
        }, 
        "fit": "linear", 
        "value": 0.027134117609373724
    }, 
    "Ar39": {
        "error": 0.008477039777349553, 
        "filter_outliers_dict": {
            "filter_outliers": true, 
            "iterations": 1, 
            "std_devs": 2
        }, 
        "fit": "Parabolic", 
        "value": -0.03626455227060856
    }, 
    "Ar40": {
        "error": 0.01330431312363046, 
        "filter_outliers_dict": {
            "filter_outliers": true, 
            "iterations": 1, 
            "std_devs": 2
        }, 
        "fit": "Parabolic", 
        "value": 82.43439034925197
    }, 
    "PM41": {
        "error": 0.06791966509024465, 
        "filter_outliers_dict": {
            "filter_outliers": false, 
            "iterations": 1, 
            "std_devs": 2
        }, 
        "fit": "linear", 
        "value": -0.16647042589927602
    }
}