{
    "Ar36": {
        "error": 0.0009355222354217654, 
        "filter_outliers_dict": {
            "filter_outliers": true, 
            "iterations": 1, 
            "std_devs": 2
        }, 
        "fit": "Parabolic", 
        "value": 0.2826257448782009
    }, 
    "Ar37": {
        "error": 0.005273890370913332, 
        "filter_outliers_dict": {
            "filter_outliers": true, 
            "iterations": 1, 
            "std_devs": 2
        }, 
        "fit": "linear", 
        "value": 0.0157881936858497
    }, 
    "Ar38": {
        "error": 0.0022761014892023015, 
        "filter_outliers_dict": {
            "filter_outliers": true, 
            "iterations": 1, 
            "std_devs": 2
        }, 
        "fit": "linear", 
        "value": 0.04496646861424153
    }, 
    "Ar39": {
        "error": 0.007805102960049895, 
        "filter_outliers_dict": {
            "filter_outliers": true, 
            "iterations": 1, 
            "std_devs": 2
        }, 
        "fit": "Parabolic", 
        "value": -0.04235373835188076
    }, 
    "Ar40": {
        "error": 0.01326923117543869, 
        "filter_outliers_dict": {
            "filter_outliers": true, 
            "iterations": 1, 
            "std_devs": 2
        }, 
        "fit": "Parabolic", 
        "value": 82.45568144079593
    }, 
    "PM41": {
        "error": 0.07275833782819181, 
        "filter_outliers_dict": {
            "filter_outliers": false, 
            "iterations": 1, 
            "std_devs": 2
        }, 
        "fit": "linear", 
        "value": -0.16060272572921183
    }
}