{
    "AX": {
        "error": 0.00628230878511744, 
        "filter_outliers_dict": {
            "filter_outliers": true, 
            "iterations": 1, 
            "std_devs": 2
        }, 
        "fit": "average", 
        "value": -0.07187871147655618
    }, 
    "CDD": {
        "error": 8.52160042207739e-06, 
        "filter_outliers_dict": {
            "filter_outliers": true, 
            "iterations": 1, 
            "std_devs": 10
        }, 
        "fit": "average", 
        "value": 2.9773082287650433e-05
    }, 
    "H1": {
        "error": 0.005107135943582208, 
        "filter_outliers_dict": {
            "filter_outliers": true, 
            "iterations": 1, 
            "std_devs": 2
        }, 
        "fit": "average", 
        "value": -0.0389220204592983
    }, 
    "H2": {
        "error": 0.008607446106813877, 
        "filter_outliers_dict": {
            "filter_outliers": true, 
            "iterations": 1, 
            "std_devs": 2
        }, 
        "fit": "average", 
        "value": -0.18976260566751044
    }, 
    "L1": {
        "error": 0.0024134829872977247, 
        "filter_outliers_dict": {
            "filter_outliers": true, 
            "iterations": 1, 
            "std_devs": 2
        }, 
        "fit": "average", 
        "value": -0.018643388220552518
    }, 
    "L2": {
        "error": 0.005889814706386458, 
        "filter_outliers_dict": {
            "filter_outliers": true, 
            "iterations": 1, 
            "std_devs": 2
        }, 
        "fit": "average", 
        "value": -0.012407131862846126
    }
}