{
    "AX": {
        "error": 0.006966960929893182, 
        "filter_outliers_dict": {
            "filter_outliers": true, 
            "iterations": 1, 
            "std_devs": 2
        }, 
        "fit": "average", 
        "value": -0.08725693895229089
    }, 
    "CDD": {
        "error": 1.1356010444516365e-05, 
        "filter_outliers_dict": {
            "filter_outliers": true, 
            "iterations": 1, 
            "std_devs": 10
        }, 
        "fit": "average", 
        "value": 4.465962354978324e-05
    }, 
    "H1": {
        "error": 0.005903916569391706, 
        "filter_outliers_dict": {
            "filter_outliers": true, 
            "iterations": 1, 
            "std_devs": 2
        }, 
        "fit": "average", 
        "value": -0.03973068108214023
    }, 
    "H2": {
        "error": 0.00645220991757776, 
        "filter_outliers_dict": {
            "filter_outliers": true, 
            "iterations": 1, 
            "std_devs": 2
        }, 
        "fit": "average", 
        "value": -0.18728620949119598
    }, 
    "L1": {
        "error": 0.0026388172676375405, 
        "filter_outliers_dict": {
            "filter_outliers": true, 
            "iterations": 1, 
            "std_devs": 2
        }, 
        "fit": "average", 
        "value": -0.02599671363784808
    }, 
    "L2": {
        "error": 0.006662433177060312, 
        "filter_outliers_dict": {
            "filter_outliers": true, 
            "iterations": 1, 
            "std_devs": 2
        }, 
        "fit": "average", 
        "value": -0.016046877536095308
    }
}