{
    "Ar40AX": {
        "error": 0.32626165391335593, 
        "filter_outliers_dict": {
            "filter_outliers": false, 
            "iterations": 1, 
            "std_devs": 2
        }, 
        "fit": "parabolic", 
        "value": 1141.206614848596
    }, 
    "Ar40H1": {
        "error": 0.40429543804063794, 
        "filter_outliers_dict": {
            "filter_outliers": false, 
            "iterations": 1, 
            "std_devs": 2
        }, 
        "fit": "parabolic", 
        "value": 1131.0985699396842
    }, 
    "Ar40L2": {
        "error": 0.42693445735670854, 
        "filter_outliers_dict": {
            "filter_outliers": false, 
            "iterations": 1, 
            "std_devs": 2
        }, 
        "fit": "parabolic", 
        "value": 1159.1545566352138
    }
}