{
    "Ar36": {
        "error": 0.0002196531094626568, 
        "filter_outliers_dict": {
            "filter_outliers": true, 
            "iterations": 1, 
            "std_devs": 2
        }, 
        "fit": "Parabolic", 
        "value": 0.009956924982743651
    }, 
    "Ar37": {
        "error": 0.005508501988824372, 
        "filter_outliers_dict": {
            "filter_outliers": true, 
            "iterations": 1, 
            "std_devs": 2
        }, 
        "fit": "linear", 
        "value": 0.029996581021792167
    }, 
    "Ar38": {
        "error": 0.00222571208952654, 
        "filter_outliers_dict": {
            "filter_outliers": true, 
            "iterations": 1, 
            "std_devs": 2
        }, 
        "fit": "linear", 
        "value": -0.012388044563929806
    }, 
    "Ar39": {
        "error": 0.008517250146241127, 
        "filter_outliers_dict": {
            "filter_outliers": true, 
            "iterations": 1, 
            "std_devs": 2
        }, 
        "fit": "Parabolic", 
        "value": -0.05617471451539891
    }, 
    "Ar40": {
        "error": 0.007340624967316698, 
        "filter_outliers_dict": {
            "filter_outliers": true, 
            "iterations": 1, 
            "std_devs": 2
        }, 
        "fit": "Parabolic", 
        "value": 1.4297272879762626
    }, 
    "PM41": {
        "error": 0.06294409855448492, 
        "filter_outliers_dict": {
            "filter_outliers": false, 
            "iterations": 1, 
            "std_devs": 2
        }, 
        "fit": "linear", 
        "value": -0.1576853502680264
    }
}