{
    "Ar36": {
        "error": 0.00040066612362026863, 
        "filter_outliers_dict": {
            "filter_outliers": true, 
            "iterations": 1, 
            "std_devs": 2
        }, 
        "fit": "Linear", 
        "value": 0.028996102340949355
    }, 
    "Ar37": {
        "error": 0.011095346453316942, 
        "filter_outliers_dict": {
            "filter_outliers": true, 
            "iterations": 1, 
            "std_devs": 2
        }, 
        "fit": "linear", 
        "value": 0.8144649273685192
    }, 
    "Ar38": {
        "error": 0.0062314316726406775, 
        "filter_outliers_dict": {
            "filter_outliers": true, 
            "iterations": 1, 
            "std_devs": 2
        }, 
        "fit": "linear", 
        "value": 4.5213781404387845
    }, 
    "Ar39": {
        "error": 0.03454150167612591, 
        "filter_outliers_dict": {
            "filter_outliers": true, 
            "iterations": 1, 
            "std_devs": 2
        }, 
        "fit": "Linear", 
        "value": 340.76782271889795
    }, 
    "Ar40": {
        "error": 0.06675251368994191, 
        "filter_outliers_dict": {
            "filter_outliers": true, 
            "iterations": 1, 
            "std_devs": 2
        }, 
        "fit": "Linear", 
        "value": 1390.3594470725384
    }, 
    "PM41": {
        "error": 0.07480338343152604, 
        "filter_outliers_dict": {
            "filter_outliers": false, 
            "iterations": 1, 
            "std_devs": 2
        }, 
        "fit": "linear", 
        "value": -0.1226800552186231
    }
}